MANIFEST.in
README
additional_requirements.txt
requirements.txt
setup.py
wanabrain/__init__.py
wanabrain.egg-info/PKG-INFO
wanabrain.egg-info/SOURCES.txt
wanabrain.egg-info/dependency_links.txt
wanabrain.egg-info/not-zip-safe
wanabrain.egg-info/requires.txt
wanabrain.egg-info/top_level.txt
wanabrain/graph_parser/__init__.py
wanabrain/graph_parser/data_provider.py
wanabrain/graph_parser/db_manager.py
wanabrain/graph_parser/exceptions.py
wanabrain/graph_parser/factory.py
wanabrain/graph_parser/graph_browser.py
wanabrain/graph_parser/image_processer.py
wanabrain/graph_parser/interpreter.py
wanabrain/graph_parser/motion.py
wanabrain/graph_parser/network_evaluator.py
wanabrain/graph_parser/network_trainer.py
wanabrain/graph_parser/os_manager.py
wanabrain/graph_parser/reporter.py
wanabrain/graph_parser/sequence_input_layer.py
wanabrain/graph_parser/settings.ini
wanabrain/graph_parser/settings.py
wanabrain/graph_parser/utils.py
wanabrain/graph_parser/visualizator.py
wanabrain/graph_parser/tests/__init__.py
wanabrain/graph_parser/tests/factory.py
wanabrain/graph_parser/tests/graph_browser.py
wanabrain/graph_parser/tests/interpreter.py
wanabrain/graph_parser/tests/network_evaluator.py
wanabrain/graph_parser/tests/visualize.py
wanabrain/video_parser/__init__.py
wanabrain/video_parser/clustering.py
wanabrain/video_parser/key_frames.py
wanabrain/video_parser/landscape_training.py
wanabrain/video_parser/motion_detection.py
wanabrain/video_parser/themes_classification.py
wanabrain/video_parser/video_parser.py
wanabrain/video_parser/tests/__init__.py
wanabrain/video_parser/tests/get_tags.py