Metadata-Version: 1.0
Name: wanabrain
Version: 0.1.2
Summary: Deep Learning algorithms for video processing tasks
Home-page: UNKNOWN
Author: Léo Vetter
Author-email: vetter.leo@gmail.com
License: MIT
Platform: UNKNOWN
